{
  "movie": {
    "precision": 1.0,
    "recall": 1.0,
    "f1-score": 1.0,
    "support": 4172,
    "confused_with": {}
  },
  "person": {
    "precision": 1.0,
    "recall": 1.0,
    "f1-score": 1.0,
    "support": 990,
    "confused_with": {}
  },
  "micro avg": {
    "precision": 1.0,
    "recall": 1.0,
    "f1-score": 1.0,
    "support": 5162
  },
  "macro avg": {
    "precision": 1.0,
    "recall": 1.0,
    "f1-score": 1.0,
    "support": 5162
  },
  "weighted avg": {
    "precision": 1.0,
    "recall": 1.0,
    "f1-score": 1.0,
    "support": 5162
  }
}